<!-- Disruptor Appender -->
<included>
    <appender name="DISRUPTOR_CONSOLE" class="net.logstash.logback.appender.LoggingEventAsyncDisruptorAppender">
        <appender-ref ref="CONSOLE" />
    </appender>
    <appender name="DISRUPTOR_FILE" class="net.logstash.logback.appender.LoggingEventAsyncDisruptorAppender">
        <appender-ref ref="FILE" />
    </appender>
    <appender name="DISRUPTOR_ERROR_FILE" class="net.logstash.logback.appender.LoggingEventAsyncDisruptorAppender">
        <appender-ref ref="FILE" />
    </appender>
</included>